qwen_asr/__init__.py
qwen_asr/__main__.py
qwen_asr/cli/demo.py
qwen_asr/cli/demo_streaming.py
qwen_asr/cli/serve.py
qwen_asr/core/transformers_backend/__init__.py
qwen_asr/core/transformers_backend/configuration_qwen3_asr.py
qwen_asr/core/transformers_backend/modeling_qwen3_asr.py
qwen_asr/core/transformers_backend/processing_qwen3_asr.py
qwen_asr/core/vllm_backend/__init__.py
qwen_asr/core/vllm_backend/qwen3_asr.py
qwen_asr/inference/qwen3_asr.py
qwen_asr/inference/qwen3_forced_aligner.py
qwen_asr/inference/utils.py
qwen_asr/inference/assets/korean_dict_jieba.dict
qwen_asr-0.0.5.dist-info/licenses/LICENSE
qwen_asr-0.0.5.dist-info/METADATA
qwen_asr-0.0.5.dist-info/WHEEL
qwen_asr-0.0.5.dist-info/entry_points.txt
qwen_asr-0.0.5.dist-info/top_level.txt
qwen_asr-0.0.5.dist-info/RECORD
